[
  {
    "productId": 1761589031972,
    "batchId": 1761589535098,
    "barcode": "BATCH1761589535098-01",
    "costPrice": 1500,
    "sellingPrice": 2000,
    "location": "Uttara",
    "status": "sold",
    "admittedAt": "2025-10-27T18:32:16.268Z",
    "id": 1761589607166,
    "createdAt": "2025-10-27T18:28:15.360Z",
    "updatedAt": "2025-10-27T18:40:13.880Z",
    "soldAt": "2025-10-27T18:40:13.491Z"
  },
  {
    "productId": 1761589031972,
    "batchId": 1761589535098,
    "barcode": "BATCH1761589535098-02",
    "costPrice": 1500,
    "sellingPrice": 2000,
    "location": "Uttara",
    "status": "sold",
    "admittedAt": "2025-10-27T18:32:18.930Z",
    "id": 1761589609267,
    "createdAt": "2025-10-27T18:28:15.360Z",
    "updatedAt": "2025-10-27T18:41:08.512Z",
    "orderId": 1761590468510,
    "soldAt": "2025-10-27T18:41:08.512Z"
  },
  {
    "productId": 1761589031972,
    "batchId": 1761589535098,
    "barcode": "BATCH1761589535098-03",
    "costPrice": 1500,
    "sellingPrice": 2000,
    "location": "Uttara",
    "status": "sold",
    "admittedAt": "2025-10-27T18:32:22.330Z",
    "id": 1761589611537,
    "createdAt": "2025-10-27T18:28:15.360Z",
    "updatedAt": "2025-10-27T18:52:22.038Z",
    "orderId": 1761591142036,
    "soldAt": "2025-10-27T18:52:22.038Z"
  },
  {
    "productId": 1761589031972,
    "batchId": 1761589535098,
    "barcode": "BATCH1761589535098-04",
    "costPrice": 1500,
    "sellingPrice": 2000,
    "location": "Uttara",
    "status": "available",
    "admittedAt": "2025-10-27T18:32:24.888Z",
    "id": 1761589613472,
    "createdAt": "2025-10-27T18:28:15.360Z",
    "updatedAt": "2025-10-27T18:32:25.257Z"
  },
  {
    "productId": 1761589031972,
    "batchId": 1761589535098,
    "barcode": "BATCH1761589535098-05",
    "costPrice": 1500,
    "sellingPrice": 2000,
    "location": "Uttara",
    "status": "available",
    "admittedAt": "2025-10-27T18:32:27.064Z",
    "id": 1761589617197,
    "createdAt": "2025-10-27T18:28:15.360Z",
    "updatedAt": "2025-10-27T18:32:27.446Z"
  },
  {
    "productId": 1761589031972,
    "batchId": 1761589535098,
    "barcode": "BATCH1761589535098-06",
    "costPrice": 1500,
    "sellingPrice": 2000,
    "location": "Uttara",
    "status": "available",
    "admittedAt": "2025-10-27T18:32:29.704Z",
    "id": 1761589620831,
    "createdAt": "2025-10-27T18:28:15.360Z",
    "updatedAt": "2025-10-27T18:32:30.089Z"
  },
  {
    "productId": 1761589031972,
    "batchId": 1761589535098,
    "barcode": "BATCH1761589535098-07",
    "costPrice": 1500,
    "sellingPrice": 2000,
    "location": "Uttara",
    "status": "defective",
    "admittedAt": "2025-10-27T18:32:39.348Z",
    "id": 1761589623321,
    "createdAt": "2025-10-27T18:28:15.360Z",
    "updatedAt": "2025-10-27T18:42:19.705Z"
  },
  {
    "productId": 1761589326964,
    "batchId": 1761589571631,
    "barcode": "BATCH1761589571631-01",
    "costPrice": 900,
    "sellingPrice": 1500,
    "location": "Mohammapur",
    "status": "defective",
    "admittedAt": "2025-10-27T18:27:13.028Z",
    "id": 1761589633398,
    "createdAt": "2025-10-27T18:27:13.398Z",
    "soldAt": "2025-10-27T18:39:15.032Z",
    "updatedAt": "2025-10-27T18:45:50.776Z"
  },
  {
    "productId": 1761589326964,
    "batchId": 1761589571631,
    "barcode": "BATCH1761589571631-02",
    "costPrice": 900,
    "sellingPrice": 1500,
    "location": "Mohammapur",
    "status": "available",
    "admittedAt": "2025-10-27T18:27:15.030Z",
    "id": 1761589635404,
    "createdAt": "2025-10-27T18:27:15.404Z"
  },
  {
    "productId": 1761589326964,
    "batchId": 1761589571631,
    "barcode": "BATCH1761589571631-03",
    "costPrice": 900,
    "sellingPrice": 1500,
    "location": "Mohammapur",
    "status": "available",
    "admittedAt": "2025-10-27T18:27:17.350Z",
    "id": 1761589637736,
    "createdAt": "2025-10-27T18:27:17.736Z"
  },
  {
    "productId": 1761589326964,
    "batchId": 1761589571631,
    "barcode": "BATCH1761589571631-04",
    "costPrice": 900,
    "sellingPrice": 1500,
    "location": "Mohammapur",
    "status": "available",
    "admittedAt": "2025-10-27T18:27:19.721Z",
    "id": 1761589640078,
    "createdAt": "2025-10-27T18:27:20.078Z"
  },
  {
    "productId": 1761589326964,
    "batchId": 1761589571631,
    "barcode": "BATCH1761589571631-05",
    "costPrice": 900,
    "sellingPrice": 1500,
    "location": "Mohammapur",
    "status": "available",
    "admittedAt": "2025-10-27T18:27:23.572Z",
    "id": 1761589643955,
    "createdAt": "2025-10-27T18:27:23.955Z"
  },
  {
    "productId": 1761589495801,
    "batchId": 1761589593751,
    "barcode": "BATCH1761589593751-01",
    "costPrice": 200,
    "sellingPrice": 300,
    "location": "Uttara",
    "status": "sold",
    "admittedAt": "2025-10-27T18:32:41.968Z",
    "id": 1761589652391,
    "createdAt": "2025-10-27T18:28:15.360Z",
    "updatedAt": "2025-10-27T18:55:26.145Z",
    "orderId": 1761591326143,
    "soldAt": "2025-10-27T18:55:26.145Z"
  },
  {
    "productId": 1761589495801,
    "batchId": 1761589593751,
    "barcode": "BATCH1761589593751-02",
    "costPrice": 200,
    "sellingPrice": 300,
    "location": "Uttara",
    "status": "available",
    "admittedAt": "2025-10-27T18:32:46.580Z",
    "id": 1761589654803,
    "createdAt": "2025-10-27T18:28:15.360Z",
    "updatedAt": "2025-10-27T18:32:46.931Z"
  },
  {
    "productId": 1761589495801,
    "batchId": 1761589593751,
    "barcode": "BATCH1761589593751-03",
    "costPrice": 200,
    "sellingPrice": 300,
    "location": "Uttara",
    "status": "available",
    "admittedAt": "2025-10-27T18:32:48.296Z",
    "id": 1761589658369,
    "createdAt": "2025-10-27T18:28:15.360Z",
    "updatedAt": "2025-10-27T18:32:48.684Z"
  },
  {
    "productId": 1761589495801,
    "batchId": 1761589593751,
    "barcode": "BATCH1761589593751-04",
    "costPrice": 200,
    "sellingPrice": 300,
    "location": "Uttara",
    "status": "available",
    "admittedAt": "2025-10-27T18:32:51.896Z",
    "id": 1761589660672,
    "createdAt": "2025-10-27T18:28:15.360Z",
    "updatedAt": "2025-10-27T18:32:52.262Z"
  },
  {
    "productId": 1761589495801,
    "batchId": 1761589593751,
    "barcode": "BATCH1761589593751-05",
    "costPrice": 200,
    "sellingPrice": 300,
    "location": "Uttara",
    "status": "available",
    "admittedAt": "2025-10-27T18:32:54.673Z",
    "id": 1761589662718,
    "createdAt": "2025-10-27T18:28:15.360Z",
    "updatedAt": "2025-10-27T18:32:55.069Z"
  }
]