[
  {
    "id": 1761336981057,
    "salesBy": "E-Commerce Order",
    "date": "2025-10-24",
    "customer": {
      "name": "Adrita Ahsan",
      "email": "adrita06@gmail.com",
      "phone": "01745191964"
    },
    "deliveryAddress": {
      "division": "Dhaka",
      "district": "Dhaka",
      "city": "",
      "zone": "Dhaka",
      "area": "Kallyanpur",
      "address": "Flat no. B2",
      "postalCode": "1207"
    },
    "products": [
      {
        "productId": 1761287820536,
        "productName": "Katha Stich",
        "size": "N/A",
        "qty": 1,
        "price": 5000,
        "discount": 0,
        "amount": 5000,
        "barcodes": [
          "BATCH1761335605648-01"
        ]
      },
      {
        "productId": 1761284271565,
        "productName": "Toshor Silk-Red",
        "size": "N/A",
        "qty": 1,
        "price": 1300,
        "discount": 0,
        "amount": 1300,
        "barcodes": [
          "BATCH1761335622190-01"
        ]
      }
    ],
    "subtotal": 6300,
    "amounts": {
      "subtotal": 6300,
      "totalDiscount": 0,
      "vat": 0,
      "vatRate": 0,
      "transportCost": 0,
      "total": 6300
    },
    "payments": {
      "sslCommerz": 0,
      "advance": 0,
      "transactionId": "",
      "totalPaid": 0,
      "due": 6300
    },
    "createdAt": "2025-10-24T20:16:21.066Z"
  },
  {
    "id": 1761375257234,
    "userId": "1761340110643",
    "salesBy": "E-Commerce Order",
    "date": "2025-10-25",
    "customer": {
      "name": "adrita_ahsan",
      "email": "adritaahsan06@gmail.com",
      "phone": "01745191964"
    },
    "deliveryAddress": {
      "division": "Dhaka",
      "district": "Dhaka",
      "city": "Dhaka",
      "zone": "",
      "area": "Kallyanpur",
      "address": "House#18/3, Flat#B2, Mainroad, Kallyanpur, Dhaka",
      "postalCode": "1207"
    },
    "products": [
      {
        "productId": 1761287820536,
        "productName": "Katha Stich",
        "size": "N/A",
        "qty": 1,
        "price": 5000,
        "discount": 0,
        "amount": 5000,
        "barcodes": [
          "BATCH1761335605648-02"
        ]
      }
    ],
    "subtotal": 5000,
    "amounts": {
      "subtotal": 5000,
      "totalDiscount": 0,
      "vat": 0,
      "vatRate": 0,
      "transportCost": 0,
      "total": 5000
    },
    "payments": {
      "sslCommerz": 0,
      "advance": 0,
      "transactionId": "",
      "totalPaid": 0,
      "due": 5000
    },
    "createdAt": "2025-10-25T06:54:17.239Z"
  },
  {
    "id": 1761541893762,
    "userId": null,
    "salesBy": "E-Commerce Order",
    "date": "2025-10-27",
    "customer": {
      "name": "Adrita Ahsan",
      "email": "adritaahsan06@gmail.com",
      "phone": "01745191964"
    },
    "deliveryAddress": {
      "division": "Dhaka",
      "district": "Dhaka",
      "city": "Dhaka",
      "zone": "",
      "area": "Kallyanpur",
      "address": "House#18/3",
      "postalCode": "1207"
    },
    "products": [
      {
        "productId": 1761284271565,
        "productName": "Toshor Silk-Red",
        "size": "N/A",
        "qty": 3,
        "price": 1300,
        "discount": 0,
        "amount": 3900,
        "barcodes": [
          "BATCH1761335622190-02",
          "BATCH1761335622190-03",
          "BATCH1761335622190-04"
        ]
      },
      {
        "productId": 1761287820536,
        "productName": "Katha Stich",
        "size": "N/A",
        "qty": 1,
        "price": 5000,
        "discount": 0,
        "amount": 5000,
        "barcodes": [
          "BATCH1761335605648-03"
        ]
      }
    ],
    "subtotal": 8900,
    "amounts": {
      "subtotal": 8900,
      "totalDiscount": 0,
      "vat": 0,
      "vatRate": 0,
      "transportCost": 0,
      "total": 8900
    },
    "payments": {
      "sslCommerz": 0,
      "advance": 0,
      "transactionId": "",
      "totalPaid": 0,
      "due": 8900
    },
    "createdAt": "2025-10-27T05:11:33.765Z"
  }
]